taggable/__init__.py
taggable/taggable_sequence.py
taggable/taggable_string.py
taggable-0.2.0.dist-info/DESCRIPTION.rst
taggable-0.2.0.dist-info/METADATA
taggable-0.2.0.dist-info/RECORD
taggable-0.2.0.dist-info/WHEEL
taggable-0.2.0.dist-info/metadata.json
taggable-0.2.0.dist-info/top_level.txt
